Metadata-Version: 1.0
Name: soyuz
Version: 0.0.1
Summary: NLTK API with SpaCy models.
Home-page: https://github.com/alvations/soyuz
Author: UNKNOWN
Author-email: UNKNOWN
License: UNKNOWN
Platform: UNKNOWN
